PDFParser007/PDFParser007.py
PDFParser007/__init__.py
PDFParser007-0.0.2.dist-info/LICENSE.txt
PDFParser007-0.0.2.dist-info/METADATA
PDFParser007-0.0.2.dist-info/WHEEL
PDFParser007-0.0.2.dist-info/top_level.txt
PDFParser007-0.0.2.dist-info/RECORD
